xersplitter/Splitter.py
xersplitter/__init__.py
xersplitter-1.0.1.dist-info/LICENSE
xersplitter-1.0.1.dist-info/METADATA
xersplitter-1.0.1.dist-info/WHEEL
xersplitter-1.0.1.dist-info/entry_points.txt
xersplitter-1.0.1.dist-info/top_level.txt
xersplitter-1.0.1.dist-info/RECORD
