Metadata-Version: 2.1
Name: xersplitter
Version: 1.0.1
Summary: Split your Primavera P6 .XER files into CSV or XLSX files
Home-page: http://github.com/JaiLaff/XER-Splitter
Author: Jai Lafferty
Author-email: jai.lafferty@gmail.com
License: GPLv3
Platform: UNKNOWN
Classifier: License :: OSI Approved :: GNU General Public License v3 (GPLv3)
Classifier: Programming Language :: Python :: 3
Classifier: Operating System :: OS Independent
Classifier: Natural Language :: English
Classifier: Development Status :: 5 - Production/Stable
Requires-Python: >=3.6
